[
  {
    "avg_local_confirmation": 0.67007,
    "executed_local_confirmation": 1,
    "family": "dio_0byw",
    "long_local": 1,
    "max_local_confirmation": 0.67007,
    "observed_related_potential": 0,
    "phase_count": 1,
    "phases": "referenz",
    "reward_sum": 7.904152,
    "rows": 1,
    "short_local": 0,
    "top_conflict_count": 1,
    "top_conflict_family": "dio_0n4c",
    "top_support_count": 1,
    "top_support_family": "dio_052z",
    "unconfirmed": 0,
    "unexecuted_local_potential": 0
  },
  {
    "avg_local_confirmation": 0.575538,
    "executed_local_confirmation": 1,
    "family": "dio_1r0h",
    "long_local": 0,
    "max_local_confirmation": 0.575538,
    "observed_related_potential": 0,
    "phase_count": 1,
    "phases": "rauschen",
    "reward_sum": 3.275704,
    "rows": 1,
    "short_local": 1,
    "top_conflict_count": 1,
    "top_conflict_family": "dio_0byw",
    "top_support_count": 1,
    "top_support_family": "dio_0n4c",
    "unconfirmed": 0,
    "unexecuted_local_potential": 0
  },
  {
    "avg_local_confirmation": 0.567726,
    "executed_local_confirmation": 1,
    "family": "dio_0n4c",
    "long_local": 0,
    "max_local_confirmation": 0.567726,
    "observed_related_potential": 0,
    "phase_count": 1,
    "phases": "varianz",
    "reward_sum": 2.938984,
    "rows": 1,
    "short_local": 1,
    "top_conflict_count": 1,
    "top_conflict_family": "dio_0byw",
    "top_support_count": 1,
    "top_support_family": "dio_1r0h",
    "unconfirmed": 0,
    "unexecuted_local_potential": 0
  },
  {
    "avg_local_confirmation": 0.531942,
    "executed_local_confirmation": 1,
    "family": "dio_052z",
    "long_local": 1,
    "max_local_confirmation": 0.531942,
    "observed_related_potential": 0,
    "phase_count": 1,
    "phases": "sensorische_varianz",
    "reward_sum": 2.162886,
    "rows": 1,
    "short_local": 0,
    "top_conflict_count": 1,
    "top_conflict_family": "dio_0n4c",
    "top_support_count": 1,
    "top_support_family": "dio_0byw",
    "unconfirmed": 0,
    "unexecuted_local_potential": 0
  },
  {
    "avg_local_confirmation": 0.49903,
    "executed_local_confirmation": 1,
    "family": "dio_0lt6",
    "long_local": 0,
    "max_local_confirmation": 0.49903,
    "observed_related_potential": 0,
    "phase_count": 1,
    "phases": "referenz",
    "reward_sum": 2.130489,
    "rows": 1,
    "short_local": 1,
    "top_conflict_count": 1,
    "top_conflict_family": "dio_0byw",
    "top_support_count": 1,
    "top_support_family": "dio_0fp8",
    "unconfirmed": 0,
    "unexecuted_local_potential": 0
  },
  {
    "avg_local_confirmation": 0.465048,
    "executed_local_confirmation": 1,
    "family": "dio_0nv8",
    "long_local": 0,
    "max_local_confirmation": 0.465048,
    "observed_related_potential": 0,
    "phase_count": 1,
    "phases": "sensorische_varianz",
    "reward_sum": 1.826216,
    "rows": 1,
    "short_local": 1,
    "top_conflict_count": 1,
    "top_conflict_family": "dio_01nf",
    "top_support_count": 1,
    "top_support_family": "dio_0vyd",
    "unconfirmed": 0,
    "unexecuted_local_potential": 0
  },
  {
    "avg_local_confirmation": 0.459745,
    "executed_local_confirmation": 1,
    "family": "dio_14zx",
    "long_local": 0,
    "max_local_confirmation": 0.459745,
    "observed_related_potential": 0,
    "phase_count": 1,
    "phases": "referenz",
    "reward_sum": 1.782506,
    "rows": 1,
    "short_local": 1,
    "top_conflict_count": 1,
    "top_conflict_family": "dio_1uez",
    "top_support_count": 1,
    "top_support_family": "dio_1bzs",
    "unconfirmed": 0,
    "unexecuted_local_potential": 0
  },
  {
    "avg_local_confirmation": 0.446938,
    "executed_local_confirmation": 1,
    "family": "dio_1uez",
    "long_local": 1,
    "max_local_confirmation": 0.446938,
    "observed_related_potential": 0,
    "phase_count": 1,
    "phases": "rauschen",
    "reward_sum": 1.446988,
    "rows": 1,
    "short_local": 0,
    "top_conflict_count": 1,
    "top_conflict_family": "dio_13wt",
    "top_support_count": 1,
    "top_support_family": "dio_1vb3",
    "unconfirmed": 0,
    "unexecuted_local_potential": 0
  },
  {
    "avg_local_confirmation": 0.445774,
    "executed_local_confirmation": 1,
    "family": "dio_179o",
    "long_local": 1,
    "max_local_confirmation": 0.445774,
    "observed_related_potential": 0,
    "phase_count": 1,
    "phases": "varianz",
    "reward_sum": 1.431863,
    "rows": 1,
    "short_local": 0,
    "top_conflict_count": 1,
    "top_conflict_family": "dio_1iuq",
    "top_support_count": 1,
    "top_support_family": "dio_1v23",
    "unconfirmed": 0,
    "unexecuted_local_potential": 0
  },
  {
    "avg_local_confirmation": 0.377189,
    "executed_local_confirmation": 1,
    "family": "dio_0uct",
    "long_local": 1,
    "max_local_confirmation": 0.377189,
    "observed_related_potential": 0,
    "phase_count": 1,
    "phases": "varianz",
    "reward_sum": 0.956362,
    "rows": 1,
    "short_local": 0,
    "top_conflict_count": 1,
    "top_conflict_family": "dio_18iw",
    "top_support_count": 1,
    "top_support_family": "dio_1mml",
    "unconfirmed": 0,
    "unexecuted_local_potential": 0
  },
  {
    "avg_local_confirmation": 0.368216,
    "executed_local_confirmation": 1,
    "family": "dio_0f4h",
    "long_local": 1,
    "max_local_confirmation": 0.368216,
    "observed_related_potential": 0,
    "phase_count": 1,
    "phases": "rauschen",
    "reward_sum": 0.817431,
    "rows": 1,
    "short_local": 0,
    "top_conflict_count": 1,
    "top_conflict_family": "dio_1144",
    "top_support_count": 1,
    "top_support_family": "dio_1vb3",
    "unconfirmed": 0,
    "unexecuted_local_potential": 0
  },
  {
    "avg_local_confirmation": 0.367451,
    "executed_local_confirmation": 1,
    "family": "dio_0fp8",
    "long_local": 0,
    "max_local_confirmation": 0.367451,
    "observed_related_potential": 0,
    "phase_count": 1,
    "phases": "sensorische_varianz",
    "reward_sum": 0.796759,
    "rows": 1,
    "short_local": 1,
    "top_conflict_count": 1,
    "top_conflict_family": "dio_0irs",
    "top_support_count": 1,
    "top_support_family": "dio_0lt6",
    "unconfirmed": 0,
    "unexecuted_local_potential": 0
  },
  {
    "avg_local_confirmation": 0.235885,
    "executed_local_confirmation": 0,
    "family": "dio_0irs",
    "long_local": 1,
    "max_local_confirmation": 0.235885,
    "observed_related_potential": 1,
    "phase_count": 1,
    "phases": "varianz",
    "reward_sum": 0.0,
    "rows": 1,
    "short_local": 0,
    "top_conflict_count": 1,
    "top_conflict_family": "dio_0n4c",
    "top_support_count": 1,
    "top_support_family": "dio_052z",
    "unconfirmed": 0,
    "unexecuted_local_potential": 0
  },
  {
    "avg_local_confirmation": 0.234177,
    "executed_local_confirmation": 0,
    "family": "dio_0dcm",
    "long_local": 0,
    "max_local_confirmation": 0.234177,
    "observed_related_potential": 1,
    "phase_count": 1,
    "phases": "rauschen",
    "reward_sum": 0.0,
    "rows": 1,
    "short_local": 1,
    "top_conflict_count": 1,
    "top_conflict_family": "dio_0qyu",
    "top_support_count": 1,
    "top_support_family": "dio_1r0h",
    "unconfirmed": 0,
    "unexecuted_local_potential": 0
  },
  {
    "avg_local_confirmation": 0.231742,
    "executed_local_confirmation": 0,
    "family": "dio_1sxo",
    "long_local": 0,
    "max_local_confirmation": 0.231742,
    "observed_related_potential": 1,
    "phase_count": 1,
    "phases": "rauschen",
    "reward_sum": 0.0,
    "rows": 1,
    "short_local": 1,
    "top_conflict_count": 1,
    "top_conflict_family": "dio_0qyu",
    "top_support_count": 1,
    "top_support_family": "dio_1r0h",
    "unconfirmed": 0,
    "unexecuted_local_potential": 0
  },
  {
    "avg_local_confirmation": 0.231441,
    "executed_local_confirmation": 0,
    "family": "dio_1j78",
    "long_local": 1,
    "max_local_confirmation": 0.231441,
    "observed_related_potential": 1,
    "phase_count": 1,
    "phases": "rauschen",
    "reward_sum": 0.0,
    "rows": 1,
    "short_local": 0,
    "top_conflict_count": 1,
    "top_conflict_family": "dio_18iw",
    "top_support_count": 1,
    "top_support_family": "dio_0uct",
    "unconfirmed": 0,
    "unexecuted_local_potential": 0
  },
  {
    "avg_local_confirmation": 0.23047,
    "executed_local_confirmation": 0,
    "family": "dio_1mml",
    "long_local": 1,
    "max_local_confirmation": 0.23047,
    "observed_related_potential": 1,
    "phase_count": 1,
    "phases": "rauschen",
    "reward_sum": 0.0,
    "rows": 1,
    "short_local": 0,
    "top_conflict_count": 1,
    "top_conflict_family": "dio_18iw",
    "top_support_count": 1,
    "top_support_family": "dio_0uct",
    "unconfirmed": 0,
    "unexecuted_local_potential": 0
  },
  {
    "avg_local_confirmation": 0.230271,
    "executed_local_confirmation": 0,
    "family": "dio_0309",
    "long_local": 0,
    "max_local_confirmation": 0.230271,
    "observed_related_potential": 1,
    "phase_count": 1,
    "phases": "rauschen",
    "reward_sum": 0.0,
    "rows": 1,
    "short_local": 1,
    "top_conflict_count": 1,
    "top_conflict_family": "dio_1j78",
    "top_support_count": 1,
    "top_support_family": "dio_18iw",
    "unconfirmed": 0,
    "unexecuted_local_potential": 0
  },
  {
    "avg_local_confirmation": 0.229619,
    "executed_local_confirmation": 0,
    "family": "dio_13wt",
    "long_local": 0,
    "max_local_confirmation": 0.229619,
    "observed_related_potential": 1,
    "phase_count": 1,
    "phases": "varianz",
    "reward_sum": 0.0,
    "rows": 1,
    "short_local": 1,
    "top_conflict_count": 1,
    "top_conflict_family": "dio_1tg9",
    "top_support_count": 1,
    "top_support_family": "dio_0nv8",
    "unconfirmed": 0,
    "unexecuted_local_potential": 0
  },
  {
    "avg_local_confirmation": 0.229016,
    "executed_local_confirmation": 0,
    "family": "dio_18iw",
    "long_local": 0,
    "max_local_confirmation": 0.229016,
    "observed_related_potential": 1,
    "phase_count": 1,
    "phases": "sensorische_varianz",
    "reward_sum": 0.0,
    "rows": 1,
    "short_local": 1,
    "top_conflict_count": 1,
    "top_conflict_family": "dio_1j78",
    "top_support_count": 1,
    "top_support_family": "dio_0309",
    "unconfirmed": 0,
    "unexecuted_local_potential": 0
  },
  {
    "avg_local_confirmation": 0.228466,
    "executed_local_confirmation": 0,
    "family": "dio_0vyd",
    "long_local": 0,
    "max_local_confirmation": 0.228466,
    "observed_related_potential": 1,
    "phase_count": 1,
    "phases": "varianz",
    "reward_sum": 0.0,
    "rows": 1,
    "short_local": 1,
    "top_conflict_count": 1,
    "top_conflict_family": "dio_0wsj",
    "top_support_count": 1,
    "top_support_family": "dio_0nv8",
    "unconfirmed": 0,
    "unexecuted_local_potential": 0
  },
  {
    "avg_local_confirmation": 0.228234,
    "executed_local_confirmation": 0,
    "family": "dio_081d",
    "long_local": 1,
    "max_local_confirmation": 0.228234,
    "observed_related_potential": 1,
    "phase_count": 1,
    "phases": "varianz",
    "reward_sum": 0.0,
    "rows": 1,
    "short_local": 0,
    "top_conflict_count": 1,
    "top_conflict_family": "dio_1144",
    "top_support_count": 1,
    "top_support_family": "dio_0nmi",
    "unconfirmed": 0,
    "unexecuted_local_potential": 0
  },
  {
    "avg_local_confirmation": 0.228234,
    "executed_local_confirmation": 0,
    "family": "dio_0oio",
    "long_local": 1,
    "max_local_confirmation": 0.228234,
    "observed_related_potential": 1,
    "phase_count": 1,
    "phases": "varianz",
    "reward_sum": 0.0,
    "rows": 1,
    "short_local": 0,
    "top_conflict_count": 1,
    "top_conflict_family": "dio_0rh0",
    "top_support_count": 1,
    "top_support_family": "dio_1ieq",
    "unconfirmed": 0,
    "unexecuted_local_potential": 0
  },
  {
    "avg_local_confirmation": 0.228113,
    "executed_local_confirmation": 0,
    "family": "dio_0nmi",
    "long_local": 1,
    "max_local_confirmation": 0.228113,
    "observed_related_potential": 1,
    "phase_count": 1,
    "phases": "rauschen",
    "reward_sum": 0.0,
    "rows": 1,
    "short_local": 0,
    "top_conflict_count": 1,
    "top_conflict_family": "dio_1144",
    "top_support_count": 1,
    "top_support_family": "dio_0f4h",
    "unconfirmed": 0,
    "unexecuted_local_potential": 0
  },
  {
    "avg_local_confirmation": 0.227973,
    "executed_local_confirmation": 0,
    "family": "dio_1v23",
    "long_local": 1,
    "max_local_confirmation": 0.227973,
    "observed_related_potential": 1,
    "phase_count": 1,
    "phases": "rauschen",
    "reward_sum": 0.0,
    "rows": 1,
    "short_local": 0,
    "top_conflict_count": 1,
    "top_conflict_family": "dio_1iuq",
    "top_support_count": 1,
    "top_support_family": "dio_179o",
    "unconfirmed": 0,
    "unexecuted_local_potential": 0
  },
  {
    "avg_local_confirmation": 0.227637,
    "executed_local_confirmation": 0,
    "family": "dio_07mf",
    "long_local": 1,
    "max_local_confirmation": 0.227637,
    "observed_related_potential": 1,
    "phase_count": 1,
    "phases": "varianz",
    "reward_sum": 0.0,
    "rows": 1,
    "short_local": 0,
    "top_conflict_count": 1,
    "top_conflict_family": "dio_1iuq",
    "top_support_count": 1,
    "top_support_family": "dio_1j78",
    "unconfirmed": 0,
    "unexecuted_local_potential": 0
  },
  {
    "avg_local_confirmation": 0.22749,
    "executed_local_confirmation": 0,
    "family": "dio_1ml8",
    "long_local": 1,
    "max_local_confirmation": 0.22749,
    "observed_related_potential": 1,
    "phase_count": 1,
    "phases": "sensorische_varianz",
    "reward_sum": 0.0,
    "rows": 1,
    "short_local": 0,
    "top_conflict_count": 1,
    "top_conflict_family": "dio_1144",
    "top_support_count": 1,
    "top_support_family": "dio_081d",
    "unconfirmed": 0,
    "unexecuted_local_potential": 0
  },
  {
    "avg_local_confirmation": 0.227477,
    "executed_local_confirmation": 0,
    "family": "dio_0rh0",
    "long_local": 0,
    "max_local_confirmation": 0.227477,
    "observed_related_potential": 1,
    "phase_count": 1,
    "phases": "sensorische_varianz",
    "reward_sum": 0.0,
    "rows": 1,
    "short_local": 1,
    "top_conflict_count": 1,
    "top_conflict_family": "dio_1ieq",
    "top_support_count": 1,
    "top_support_family": "dio_0lt6",
    "unconfirmed": 0,
    "unexecuted_local_potential": 0
  },
  {
    "avg_local_confirmation": 0.22709,
    "executed_local_confirmation": 0,
    "family": "dio_1vb3",
    "long_local": 1,
    "max_local_confirmation": 0.22709,
    "observed_related_potential": 1,
    "phase_count": 1,
    "phases": "rauschen",
    "reward_sum": 0.0,
    "rows": 1,
    "short_local": 0,
    "top_conflict_count": 1,
    "top_conflict_family": "dio_13wt",
    "top_support_count": 1,
    "top_support_family": "dio_0f4h",
    "unconfirmed": 0,
    "unexecuted_local_potential": 0
  },
  {
    "avg_local_confirmation": 0.227082,
    "executed_local_confirmation": 0,
    "family": "dio_07yj",
    "long_local": 1,
    "max_local_confirmation": 0.227082,
    "observed_related_potential": 1,
    "phase_count": 1,
    "phases": "sensorische_varianz",
    "reward_sum": 0.0,
    "rows": 1,
    "short_local": 0,
    "top_conflict_count": 1,
    "top_conflict_family": "dio_13wt",
    "top_support_count": 1,
    "top_support_family": "dio_1tki",
    "unconfirmed": 0,
    "unexecuted_local_potential": 0
  },
  {
    "avg_local_confirmation": 0.227007,
    "executed_local_confirmation": 0,
    "family": "dio_0b0d",
    "long_local": 0,
    "max_local_confirmation": 0.227007,
    "observed_related_potential": 1,
    "phase_count": 1,
    "phases": "sensorische_varianz",
    "reward_sum": 0.0,
    "rows": 1,
    "short_local": 1,
    "top_conflict_count": 1,
    "top_conflict_family": "dio_1uez",
    "top_support_count": 1,
    "top_support_family": "dio_0av4",
    "unconfirmed": 0,
    "unexecuted_local_potential": 0
  },
  {
    "avg_local_confirmation": 0.226922,
    "executed_local_confirmation": 0,
    "family": "dio_1at7",
    "long_local": 0,
    "max_local_confirmation": 0.226922,
    "observed_related_potential": 1,
    "phase_count": 1,
    "phases": "varianz",
    "reward_sum": 0.0,
    "rows": 1,
    "short_local": 1,
    "top_conflict_count": 1,
    "top_conflict_family": "dio_07mf",
    "top_support_count": 1,
    "top_support_family": "dio_0w1v",
    "unconfirmed": 0,
    "unexecuted_local_potential": 0
  },
  {
    "avg_local_confirmation": 0.226823,
    "executed_local_confirmation": 0,
    "family": "dio_0k53",
    "long_local": 1,
    "max_local_confirmation": 0.226823,
    "observed_related_potential": 1,
    "phase_count": 1,
    "phases": "rauschen",
    "reward_sum": 0.0,
    "rows": 1,
    "short_local": 0,
    "top_conflict_count": 1,
    "top_conflict_family": "dio_13wt",
    "top_support_count": 1,
    "top_support_family": "dio_0f4h",
    "unconfirmed": 0,
    "unexecuted_local_potential": 0
  },
  {
    "avg_local_confirmation": 0.22662,
    "executed_local_confirmation": 0,
    "family": "dio_0rgr",
    "long_local": 1,
    "max_local_confirmation": 0.22662,
    "observed_related_potential": 1,
    "phase_count": 1,
    "phases": "sensorische_varianz",
    "reward_sum": 0.0,
    "rows": 1,
    "short_local": 0,
    "top_conflict_count": 1,
    "top_conflict_family": "dio_1144",
    "top_support_count": 1,
    "top_support_family": "dio_1rka",
    "unconfirmed": 0,
    "unexecuted_local_potential": 0
  },
  {
    "avg_local_confirmation": 0.22658,
    "executed_local_confirmation": 0,
    "family": "dio_1lz7",
    "long_local": 0,
    "max_local_confirmation": 0.22658,
    "observed_related_potential": 1,
    "phase_count": 1,
    "phases": "varianz",
    "reward_sum": 0.0,
    "rows": 1,
    "short_local": 1,
    "top_conflict_count": 1,
    "top_conflict_family": "dio_0xq8",
    "top_support_count": 1,
    "top_support_family": "dio_0w1v",
    "unconfirmed": 0,
    "unexecuted_local_potential": 0
  },
  {
    "avg_local_confirmation": 0.226572,
    "executed_local_confirmation": 0,
    "family": "dio_1tg9",
    "long_local": 1,
    "max_local_confirmation": 0.226572,
    "observed_related_potential": 1,
    "phase_count": 1,
    "phases": "rauschen",
    "reward_sum": 0.0,
    "rows": 1,
    "short_local": 0,
    "top_conflict_count": 1,
    "top_conflict_family": "dio_13wt",
    "top_support_count": 1,
    "top_support_family": "dio_0k53",
    "unconfirmed": 0,
    "unexecuted_local_potential": 0
  },
  {
    "avg_local_confirmation": 0.226565,
    "executed_local_confirmation": 0,
    "family": "dio_0wsj",
    "long_local": 1,
    "max_local_confirmation": 0.226565,
    "observed_related_potential": 1,
    "phase_count": 1,
    "phases": "sensorische_varianz",
    "reward_sum": 0.0,
    "rows": 1,
    "short_local": 0,
    "top_conflict_count": 1,
    "top_conflict_family": "dio_0vyd",
    "top_support_count": 1,
    "top_support_family": "dio_01nf",
    "unconfirmed": 0,
    "unexecuted_local_potential": 0
  },
  {
    "avg_local_confirmation": 0.226549,
    "executed_local_confirmation": 0,
    "family": "dio_1ieq",
    "long_local": 1,
    "max_local_confirmation": 0.226549,
    "observed_related_potential": 1,
    "phase_count": 1,
    "phases": "sensorische_varianz",
    "reward_sum": 0.0,
    "rows": 1,
    "short_local": 0,
    "top_conflict_count": 1,
    "top_conflict_family": "dio_0rh0",
    "top_support_count": 1,
    "top_support_family": "dio_0oio",
    "unconfirmed": 0,
    "unexecuted_local_potential": 0
  },
  {
    "avg_local_confirmation": 0.226505,
    "executed_local_confirmation": 0,
    "family": "dio_0qb3",
    "long_local": 1,
    "max_local_confirmation": 0.226505,
    "observed_related_potential": 1,
    "phase_count": 1,
    "phases": "rauschen",
    "reward_sum": 0.0,
    "rows": 1,
    "short_local": 0,
    "top_conflict_count": 1,
    "top_conflict_family": "dio_0nv8",
    "top_support_count": 1,
    "top_support_family": "dio_18wf",
    "unconfirmed": 0,
    "unexecuted_local_potential": 0
  },
  {
    "avg_local_confirmation": 0.226393,
    "executed_local_confirmation": 0,
    "family": "dio_0ifl",
    "long_local": 0,
    "max_local_confirmation": 0.226393,
    "observed_related_potential": 1,
    "phase_count": 1,
    "phases": "sensorische_varianz",
    "reward_sum": 0.0,
    "rows": 1,
    "short_local": 1,
    "top_conflict_count": 1,
    "top_conflict_family": "dio_01nf",
    "top_support_count": 1,
    "top_support_family": "dio_0i5m",
    "unconfirmed": 0,
    "unexecuted_local_potential": 0
  },
  {
    "avg_local_confirmation": 0.22617,
    "executed_local_confirmation": 0,
    "family": "dio_01nf",
    "long_local": 1,
    "max_local_confirmation": 0.22617,
    "observed_related_potential": 1,
    "phase_count": 1,
    "phases": "rauschen",
    "reward_sum": 0.0,
    "rows": 1,
    "short_local": 0,
    "top_conflict_count": 1,
    "top_conflict_family": "dio_0nv8",
    "top_support_count": 1,
    "top_support_family": "dio_0wsj",
    "unconfirmed": 0,
    "unexecuted_local_potential": 0
  },
  {
    "avg_local_confirmation": 0.225937,
    "executed_local_confirmation": 0,
    "family": "dio_1iuq",
    "long_local": 0,
    "max_local_confirmation": 0.225937,
    "observed_related_potential": 1,
    "phase_count": 1,
    "phases": "sensorische_varianz",
    "reward_sum": 0.0,
    "rows": 1,
    "short_local": 1,
    "top_conflict_count": 1,
    "top_conflict_family": "dio_07mf",
    "top_support_count": 1,
    "top_support_family": "dio_0av4",
    "unconfirmed": 0,
    "unexecuted_local_potential": 0
  },
  {
    "avg_local_confirmation": 0.225645,
    "executed_local_confirmation": 0,
    "family": "dio_1rka",
    "long_local": 1,
    "max_local_confirmation": 0.225645,
    "observed_related_potential": 1,
    "phase_count": 1,
    "phases": "rauschen",
    "reward_sum": 0.0,
    "rows": 1,
    "short_local": 0,
    "top_conflict_count": 1,
    "top_conflict_family": "dio_1144",
    "top_support_count": 1,
    "top_support_family": "dio_0rgr",
    "unconfirmed": 0,
    "unexecuted_local_potential": 0
  },
  {
    "avg_local_confirmation": 0.225566,
    "executed_local_confirmation": 0,
    "family": "dio_0i5m",
    "long_local": 0,
    "max_local_confirmation": 0.225566,
    "observed_related_potential": 1,
    "phase_count": 1,
    "phases": "sensorische_varianz",
    "reward_sum": 0.0,
    "rows": 1,
    "short_local": 1,
    "top_conflict_count": 1,
    "top_conflict_family": "dio_01nf",
    "top_support_count": 1,
    "top_support_family": "dio_0ifl",
    "unconfirmed": 0,
    "unexecuted_local_potential": 0
  },
  {
    "avg_local_confirmation": 0.225145,
    "executed_local_confirmation": 0,
    "family": "dio_1bzs",
    "long_local": 0,
    "max_local_confirmation": 0.225145,
    "observed_related_potential": 1,
    "phase_count": 1,
    "phases": "sensorische_varianz",
    "reward_sum": 0.0,
    "rows": 1,
    "short_local": 1,
    "top_conflict_count": 1,
    "top_conflict_family": "dio_1uez",
    "top_support_count": 1,
    "top_support_family": "dio_14zx",
    "unconfirmed": 0,
    "unexecuted_local_potential": 0
  },
  {
    "avg_local_confirmation": 0.225103,
    "executed_local_confirmation": 0,
    "family": "dio_18wf",
    "long_local": 1,
    "max_local_confirmation": 0.225103,
    "observed_related_potential": 1,
    "phase_count": 1,
    "phases": "varianz",
    "reward_sum": 0.0,
    "rows": 1,
    "short_local": 0,
    "top_conflict_count": 1,
    "top_conflict_family": "dio_0nv8",
    "top_support_count": 1,
    "top_support_family": "dio_0qb3",
    "unconfirmed": 0,
    "unexecuted_local_potential": 0
  },
  {
    "avg_local_confirmation": 0.225097,
    "executed_local_confirmation": 0,
    "family": "dio_0v7w",
    "long_local": 0,
    "max_local_confirmation": 0.225097,
    "observed_related_potential": 1,
    "phase_count": 1,
    "phases": "referenz",
    "reward_sum": 0.0,
    "rows": 1,
    "short_local": 1,
    "top_conflict_count": 1,
    "top_conflict_family": "dio_0wsj",
    "top_support_count": 1,
    "top_support_family": "dio_0w1v",
    "unconfirmed": 0,
    "unexecuted_local_potential": 0
  },
  {
    "avg_local_confirmation": 0.224788,
    "executed_local_confirmation": 0,
    "family": "dio_0av4",
    "long_local": 0,
    "max_local_confirmation": 0.224788,
    "observed_related_potential": 1,
    "phase_count": 1,
    "phases": "sensorische_varianz",
    "reward_sum": 0.0,
    "rows": 1,
    "short_local": 1,
    "top_conflict_count": 1,
    "top_conflict_family": "dio_07mf",
    "top_support_count": 1,
    "top_support_family": "dio_0b0d",
    "unconfirmed": 0,
    "unexecuted_local_potential": 0
  },
  {
    "avg_local_confirmation": 0.221703,
    "executed_local_confirmation": 0,
    "family": "dio_0nny",
    "long_local": 1,
    "max_local_confirmation": 0.221703,
    "observed_related_potential": 1,
    "phase_count": 1,
    "phases": "referenz",
    "reward_sum": 0.0,
    "rows": 1,
    "short_local": 0,
    "top_conflict_count": 1,
    "top_conflict_family": "dio_1144",
    "top_support_count": 1,
    "top_support_family": "dio_0rgr",
    "unconfirmed": 0,
    "unexecuted_local_potential": 0
  },
  {
    "avg_local_confirmation": 0.221677,
    "executed_local_confirmation": 0,
    "family": "dio_0w1v",
    "long_local": 0,
    "max_local_confirmation": 0.221677,
    "observed_related_potential": 1,
    "phase_count": 1,
    "phases": "referenz",
    "reward_sum": 0.0,
    "rows": 1,
    "short_local": 1,
    "top_conflict_count": 1,
    "top_conflict_family": "dio_01nf",
    "top_support_count": 1,
    "top_support_family": "dio_0v7w",
    "unconfirmed": 0,
    "unexecuted_local_potential": 0
  },
  {
    "avg_local_confirmation": 0.221593,
    "executed_local_confirmation": 0,
    "family": "dio_0qyu",
    "long_local": 1,
    "max_local_confirmation": 0.221593,
    "observed_related_potential": 1,
    "phase_count": 1,
    "phases": "referenz",
    "reward_sum": 0.0,
    "rows": 1,
    "short_local": 0,
    "top_conflict_count": 1,
    "top_conflict_family": "dio_1r0h",
    "top_support_count": 1,
    "top_support_family": "dio_0byw",
    "unconfirmed": 0,
    "unexecuted_local_potential": 0
  },
  {
    "avg_local_confirmation": 0.22153,
    "executed_local_confirmation": 0,
    "family": "dio_0xq8",
    "long_local": 1,
    "max_local_confirmation": 0.22153,
    "observed_related_potential": 1,
    "phase_count": 1,
    "phases": "referenz",
    "reward_sum": 0.0,
    "rows": 1,
    "short_local": 0,
    "top_conflict_count": 1,
    "top_conflict_family": "dio_1lz7",
    "top_support_count": 1,
    "top_support_family": "dio_0rgr",
    "unconfirmed": 0,
    "unexecuted_local_potential": 0
  },
  {
    "avg_local_confirmation": 0.221493,
    "executed_local_confirmation": 0,
    "family": "dio_1tki",
    "long_local": 1,
    "max_local_confirmation": 0.221493,
    "observed_related_potential": 1,
    "phase_count": 1,
    "phases": "referenz",
    "reward_sum": 0.0,
    "rows": 1,
    "short_local": 0,
    "top_conflict_count": 1,
    "top_conflict_family": "dio_13wt",
    "top_support_count": 1,
    "top_support_family": "dio_07yj",
    "unconfirmed": 0,
    "unexecuted_local_potential": 0
  },
  {
    "avg_local_confirmation": 0.221169,
    "executed_local_confirmation": 0,
    "family": "dio_0zlr",
    "long_local": 0,
    "max_local_confirmation": 0.221169,
    "observed_related_potential": 1,
    "phase_count": 1,
    "phases": "referenz",
    "reward_sum": 0.0,
    "rows": 1,
    "short_local": 1,
    "top_conflict_count": 1,
    "top_conflict_family": "dio_1uez",
    "top_support_count": 1,
    "top_support_family": "dio_1bzs",
    "unconfirmed": 0,
    "unexecuted_local_potential": 0
  },
  {
    "avg_local_confirmation": 0.221063,
    "executed_local_confirmation": 0,
    "family": "dio_1144",
    "long_local": 0,
    "max_local_confirmation": 0.221063,
    "observed_related_potential": 1,
    "phase_count": 1,
    "phases": "referenz",
    "reward_sum": 0.0,
    "rows": 1,
    "short_local": 1,
    "top_conflict_count": 1,
    "top_conflict_family": "dio_081d",
    "top_support_count": 1,
    "top_support_family": "dio_14zx",
    "unconfirmed": 0,
    "unexecuted_local_potential": 0
  },
  {
    "avg_local_confirmation": 0.221046,
    "executed_local_confirmation": 0,
    "family": "dio_0rej",
    "long_local": 0,
    "max_local_confirmation": 0.221046,
    "observed_related_potential": 1,
    "phase_count": 1,
    "phases": "referenz",
    "reward_sum": 0.0,
    "rows": 1,
    "short_local": 1,
    "top_conflict_count": 1,
    "top_conflict_family": "dio_0wsj",
    "top_support_count": 1,
    "top_support_family": "dio_0v7w",
    "unconfirmed": 0,
    "unexecuted_local_potential": 0
  },
  {
    "avg_local_confirmation": 0.0,
    "executed_local_confirmation": 0,
    "family": "dio_11wp",
    "long_local": 0,
    "max_local_confirmation": 0.0,
    "observed_related_potential": 0,
    "phase_count": 1,
    "phases": "referenz",
    "reward_sum": 0.0,
    "rows": 1,
    "short_local": 0,
    "top_conflict_count": 0,
    "top_conflict_family": "-",
    "top_support_count": 0,
    "top_support_family": "-",
    "unconfirmed": 1,
    "unexecuted_local_potential": 0
  },
  {
    "avg_local_confirmation": 0.0,
    "executed_local_confirmation": 0,
    "family": "dio_12qo",
    "long_local": 0,
    "max_local_confirmation": 0.0,
    "observed_related_potential": 0,
    "phase_count": 1,
    "phases": "referenz",
    "reward_sum": 0.0,
    "rows": 1,
    "short_local": 0,
    "top_conflict_count": 0,
    "top_conflict_family": "-",
    "top_support_count": 0,
    "top_support_family": "-",
    "unconfirmed": 1,
    "unexecuted_local_potential": 0
  },
  {
    "avg_local_confirmation": 0.0,
    "executed_local_confirmation": 0,
    "family": "dio_1ll4",
    "long_local": 0,
    "max_local_confirmation": 0.0,
    "observed_related_potential": 0,
    "phase_count": 1,
    "phases": "sensorische_varianz",
    "reward_sum": 0.0,
    "rows": 1,
    "short_local": 0,
    "top_conflict_count": 0,
    "top_conflict_family": "-",
    "top_support_count": 0,
    "top_support_family": "-",
    "unconfirmed": 1,
    "unexecuted_local_potential": 0
  }
]