[
  {
    "actions": "LONG:4",
    "avg_entry_improvement_room": 0.002046,
    "avg_reward": 0.906071,
    "count": 4,
    "family": "dio_1d6j",
    "max_entry_improvement_room": 0.002046,
    "reward_sum": 3.624284
  },
  {
    "actions": "SHORT:1",
    "avg_entry_improvement_room": 0.001616,
    "avg_reward": 0.993834,
    "count": 1,
    "family": "dio_1sxo",
    "max_entry_improvement_room": 0.001616,
    "reward_sum": 0.993834
  },
  {
    "actions": "SHORT:2",
    "avg_entry_improvement_room": 0.001202,
    "avg_reward": 1.669852,
    "count": 2,
    "family": "dio_1ioc",
    "max_entry_improvement_room": 0.001202,
    "reward_sum": 3.339704
  }
]