{
  "boundary": {
    "influences_action": false,
    "is_gate": false,
    "is_motoric": false,
    "passive_only": true,
    "read_by_mini_dio": false,
    "writes_training_memory": false
  },
  "candidates_path": "bot_memory\\dio_mini_passive_recurrence_maturity_candidates.json",
  "debug_root": "debug\\dio_mini_context_stability_probe26_c_20260606",
  "detail": [
    {
      "action": "WAIT",
      "best_action_training": "SHORT",
      "candidate_conflict_or_new_rate": 0.0,
      "candidate_meaning_preservation_rate": 0.0,
      "candidate_passive_reife_state": "-",
      "candidate_stable_recurrence_rate": 0.0,
      "candidate_temporal_fragility": 0.0,
      "candidate_variant_capacity_rate": 0.0,
      "context_note": "dio_1rv1: keine passive Wiederkehrspur gefunden; nur beobachten.",
      "current_mcm_coherence": 0.982959,
      "current_mcm_tension": 0.083083,
      "current_observation_learning_pressure": 0.540187,
      "current_reflection_alignment": 0.76802,
      "current_trade_readiness": 0.0,
      "influences_action": 0,
      "is_gate": 0,
      "is_motoric": 0,
      "outcome_event": "NO_TRADE",
      "passive_only": 1,
      "read_by_mini_dio": 0,
      "recurrence_context_state": "recurrence_context_unknown",
      "recurrence_maturity_symbol": "-",
      "run": "dio_mini_lauf_1",
      "symbol": "dio_1rv13no",
      "symbol_family": "dio_1rv1",
      "tick": "1",
      "timestamp_ms": "1767560300000000",
      "writes_training_memory": 0
    },
    {
      "action": "WAIT",
      "best_action_training": "SHORT",
      "candidate_conflict_or_new_rate": 0.0,
      "candidate_meaning_preservation_rate": 1.0,
      "candidate_passive_reife_state": "sinnnah_variantenfaehig",
      "candidate_stable_recurrence_rate": 0.166667,
      "candidate_temporal_fragility": 1.0,
      "candidate_variant_capacity_rate": 0.833333,
      "context_note": "dio_1ull: sinnnah_variantenfaehig; Sinn-Erhalt=1.000000; stabile Wiederkehr=0.166667; Zeitfragilitaet=1.000000; passive Kontextlesung, keine Handlung.",
      "current_mcm_coherence": -0.233868,
      "current_mcm_tension": 0.104622,
      "current_observation_learning_pressure": 0.212676,
      "current_reflection_alignment": 0.878024,
      "current_trade_readiness": 0.0,
      "influences_action": 0,
      "is_gate": 0,
      "is_motoric": 0,
      "outcome_event": "NO_TRADE",
      "passive_only": 1,
      "read_by_mini_dio": 0,
      "recurrence_context_state": "recurrence_context_meaning_near",
      "recurrence_maturity_symbol": "dio_recur_18qky6h",
      "run": "dio_mini_lauf_1",
      "symbol": "dio_1ull2yv",
      "symbol_family": "dio_1ull",
      "tick": "2",
      "timestamp_ms": "1767560600000000",
      "writes_training_memory": 0
    },
    {
      "action": "WAIT",
      "best_action_training": "SHORT",
      "candidate_conflict_or_new_rate": 0.0,
      "candidate_meaning_preservation_rate": 0.0,
      "candidate_passive_reife_state": "-",
      "candidate_stable_recurrence_rate": 0.0,
      "candidate_temporal_fragility": 0.0,
      "candidate_variant_capacity_rate": 0.0,
      "context_note": "dio_14c1: keine passive Wiederkehrspur gefunden; nur beobachten.",
      "current_mcm_coherence": 0.097707,
      "current_mcm_tension": 0.356234,
      "current_observation_learning_pressure": 0.321225,
      "current_reflection_alignment": 0.831656,
      "current_trade_readiness": 0.0,
      "influences_action": 0,
      "is_gate": 0,
      "is_motoric": 0,
      "outcome_event": "NO_TRADE",
      "passive_only": 1,
      "read_by_mini_dio": 0,
      "recurrence_context_state": "recurrence_context_unknown",
      "recurrence_maturity_symbol": "-",
      "run": "dio_mini_lauf_1",
      "symbol": "dio_14c1zmg",
      "symbol_family": "dio_14c1",
      "tick": "3",
      "timestamp_ms": "1767560900000000",
      "writes_training_memory": 0
    },
    {
      "action": "WAIT",
      "best_action_training": "LONG",
      "candidate_conflict_or_new_rate": 0.166667,
      "candidate_meaning_preservation_rate": 0.833333,
      "candidate_passive_reife_state": "sinnnah_variantenfaehig",
      "candidate_stable_recurrence_rate": 0.666667,
      "candidate_temporal_fragility": 1.0,
      "candidate_variant_capacity_rate": 0.166667,
      "context_note": "dio_05k3: sinnnah_variantenfaehig; Sinn-Erhalt=0.833333; stabile Wiederkehr=0.666667; Zeitfragilitaet=1.000000; passive Kontextlesung, keine Handlung.",
      "current_mcm_coherence": 0.289756,
      "current_mcm_tension": 0.470591,
      "current_observation_learning_pressure": 0.408467,
      "current_reflection_alignment": 0.801332,
      "current_trade_readiness": 0.0,
      "influences_action": 0,
      "is_gate": 0,
      "is_motoric": 0,
      "outcome_event": "NO_TRADE",
      "passive_only": 1,
      "read_by_mini_dio": 0,
      "recurrence_context_state": "recurrence_context_meaning_near",
      "recurrence_maturity_symbol": "dio_recur_x7exs",
      "run": "dio_mini_lauf_1",
      "symbol": "dio_05k373k",
      "symbol_family": "dio_05k3",
      "tick": "4",
      "timestamp_ms": "1767561200000000",
      "writes_training_memory": 0
    },
    {
      "action": "WAIT",
      "best_action_training": "LONG",
      "candidate_conflict_or_new_rate": 0.0,
      "candidate_meaning_preservation_rate": 0.0,
      "candidate_passive_reife_state": "-",
      "candidate_stable_recurrence_rate": 0.0,
      "candidate_temporal_fragility": 0.0,
      "candidate_variant_capacity_rate": 0.0,
      "context_note": "dio_1tsz: keine passive Wiederkehrspur gefunden; nur beobachten.",
      "current_mcm_coherence": 0.992977,
      "current_mcm_tension": 0.362566,
      "current_observation_learning_pressure": 0.62276,
      "current_reflection_alignment": 0.732212,
      "current_trade_readiness": 0.0,
      "influences_action": 0,
      "is_gate": 0,
      "is_motoric": 0,
      "outcome_event": "NO_TRADE",
      "passive_only": 1,
      "read_by_mini_dio": 0,
      "recurrence_context_state": "recurrence_context_unknown",
      "recurrence_maturity_symbol": "-",
      "run": "dio_mini_lauf_1",
      "symbol": "dio_1tszbgb",
      "symbol_family": "dio_1tsz",
      "tick": "5",
      "timestamp_ms": "1767561500000000",
      "writes_training_memory": 0
    },
    {
      "action": "WAIT",
      "best_action_training": "LONG",
      "candidate_conflict_or_new_rate": 0.0,
      "candidate_meaning_preservation_rate": 0.0,
      "candidate_passive_reife_state": "-",
      "candidate_stable_recurrence_rate": 0.0,
      "candidate_temporal_fragility": 0.0,
      "candidate_variant_capacity_rate": 0.0,
      "context_note": "dio_1jba: keine passive Wiederkehrspur gefunden; nur beobachten.",
      "current_mcm_coherence": 0.392717,
      "current_mcm_tension": 0.344782,
      "current_observation_learning_pressure": 0.417723,
      "current_reflection_alignment": 0.800684,
      "current_trade_readiness": 0.0,
      "influences_action": 0,
      "is_gate": 0,
      "is_motoric": 0,
      "outcome_event": "NO_TRADE",
      "passive_only": 1,
      "read_by_mini_dio": 0,
      "recurrence_context_state": "recurrence_context_unknown",
      "recurrence_maturity_symbol": "-",
      "run": "dio_mini_lauf_1",
      "symbol": "dio_1jbaunv",
      "symbol_family": "dio_1jba",
      "tick": "6",
      "timestamp_ms": "1767561800000000",
      "writes_training_memory": 0
    },
    {
      "action": "WAIT",
      "best_action_training": "SHORT",
      "candidate_conflict_or_new_rate": 0.0,
      "candidate_meaning_preservation_rate": 0.0,
      "candidate_passive_reife_state": "-",
      "candidate_stable_recurrence_rate": 0.0,
      "candidate_temporal_fragility": 0.0,
      "candidate_variant_capacity_rate": 0.0,
      "context_note": "dio_0ic5: keine passive Wiederkehrspur gefunden; nur beobachten.",
      "current_mcm_coherence": -0.209546,
      "current_mcm_tension": 0.128454,
      "current_observation_learning_pressure": 0.218907,
      "current_reflection_alignment": 0.875119,
      "current_trade_readiness": 0.0,
      "influences_action": 0,
      "is_gate": 0,
      "is_motoric": 0,
      "outcome_event": "NO_TRADE",
      "passive_only": 1,
      "read_by_mini_dio": 0,
      "recurrence_context_state": "recurrence_context_unknown",
      "recurrence_maturity_symbol": "-",
      "run": "dio_mini_lauf_1",
      "symbol": "dio_0ic5er6",
      "symbol_family": "dio_0ic5",
      "tick": "7",
      "timestamp_ms": "1767562100000000",
      "writes_training_memory": 0
    },
    {
      "action": "WAIT",
      "best_action_training": "SHORT",
      "candidate_conflict_or_new_rate": 0.0,
      "candidate_meaning_preservation_rate": 0.0,
      "candidate_passive_reife_state": "-",
      "candidate_stable_recurrence_rate": 0.0,
      "candidate_temporal_fragility": 0.0,
      "candidate_variant_capacity_rate": 0.0,
      "context_note": "dio_0s84: keine passive Wiederkehrspur gefunden; nur beobachten.",
      "current_mcm_coherence": 0.395847,
      "current_mcm_tension": 0.262513,
      "current_observation_learning_pressure": 0.4449,
      "current_reflection_alignment": 0.795753,
      "current_trade_readiness": 0.0,
      "influences_action": 0,
      "is_gate": 0,
      "is_motoric": 0,
      "outcome_event": "NO_TRADE",
      "passive_only": 1,
      "read_by_mini_dio": 0,
      "recurrence_context_state": "recurrence_context_unknown",
      "recurrence_maturity_symbol": "-",
      "run": "dio_mini_lauf_1",
      "symbol": "dio_0s84lnj",
      "symbol_family": "dio_0s84",
      "tick": "8",
      "timestamp_ms": "1767562400000000",
      "writes_training_memory": 0
    },
    {
      "action": "WAIT",
      "best_action_training": "SHORT",
      "candidate_conflict_or_new_rate": 0.0,
      "candidate_meaning_preservation_rate": 1.0,
      "candidate_passive_reife_state": "sinnnah_variantenfaehig",
      "candidate_stable_recurrence_rate": 0.166667,
      "candidate_temporal_fragility": 1.0,
      "candidate_variant_capacity_rate": 0.833333,
      "context_note": "dio_19mp: sinnnah_variantenfaehig; Sinn-Erhalt=1.000000; stabile Wiederkehr=0.166667; Zeitfragilitaet=1.000000; passive Kontextlesung, keine Handlung.",
      "current_mcm_coherence": 0.372062,
      "current_mcm_tension": 0.376867,
      "current_observation_learning_pressure": 0.431111,
      "current_reflection_alignment": 0.795486,
      "current_trade_readiness": 0.0,
      "influences_action": 0,
      "is_gate": 0,
      "is_motoric": 0,
      "outcome_event": "NO_TRADE",
      "passive_only": 1,
      "read_by_mini_dio": 0,
      "recurrence_context_state": "recurrence_context_meaning_near",
      "recurrence_maturity_symbol": "dio_recur_cslksc",
      "run": "dio_mini_lauf_1",
      "symbol": "dio_19mpp0p",
      "symbol_family": "dio_19mp",
      "tick": "9",
      "timestamp_ms": "1767562700000000",
      "writes_training_memory": 0
    },
    {
      "action": "WAIT",
      "best_action_training": "LONG",
      "candidate_conflict_or_new_rate": 0.166667,
      "candidate_meaning_preservation_rate": 0.833333,
      "candidate_passive_reife_state": "sinnnah_variantenfaehig",
      "candidate_stable_recurrence_rate": 0.166667,
      "candidate_temporal_fragility": 1.0,
      "candidate_variant_capacity_rate": 0.666667,
      "context_note": "dio_1hs5: sinnnah_variantenfaehig; Sinn-Erhalt=0.833333; stabile Wiederkehr=0.166667; Zeitfragilitaet=1.000000; passive Kontextlesung, keine Handlung.",
      "current_mcm_coherence": -0.220085,
      "current_mcm_tension": 0.194834,
      "current_observation_learning_pressure": 0.222348,
      "current_reflection_alignment": 0.871524,
      "current_trade_readiness": 0.0,
      "influences_action": 0,
      "is_gate": 0,
      "is_motoric": 0,
      "outcome_event": "NO_TRADE",
      "passive_only": 1,
      "read_by_mini_dio": 0,
      "recurrence_context_state": "recurrence_context_meaning_near",
      "recurrence_maturity_symbol": "dio_recur_2rlxa4",
      "run": "dio_mini_lauf_1",
      "symbol": "dio_1hs5sz6",
      "symbol_family": "dio_1hs5",
      "tick": "10",
      "timestamp_ms": "1767563000000000",
      "writes_training_memory": 0
    },
    {
      "action": "WAIT",
      "best_action_training": "LONG",
      "candidate_conflict_or_new_rate": 0.0,
      "candidate_meaning_preservation_rate": 0.0,
      "candidate_passive_reife_state": "-",
      "candidate_stable_recurrence_rate": 0.0,
      "candidate_temporal_fragility": 0.0,
      "candidate_variant_capacity_rate": 0.0,
      "context_note": "dio_12dn: keine passive Wiederkehrspur gefunden; nur beobachten.",
      "current_mcm_coherence": 0.369061,
      "current_mcm_tension": 0.254875,
      "current_observation_learning_pressure": 0.407381,
      "current_reflection_alignment": 0.807412,
      "current_trade_readiness": 0.0,
      "influences_action": 0,
      "is_gate": 0,
      "is_motoric": 0,
      "outcome_event": "NO_TRADE",
      "passive_only": 1,
      "read_by_mini_dio": 0,
      "recurrence_context_state": "recurrence_context_unknown",
      "recurrence_maturity_symbol": "-",
      "run": "dio_mini_lauf_1",
      "symbol": "dio_12dnns3",
      "symbol_family": "dio_12dn",
      "tick": "11",
      "timestamp_ms": "1767563300000000",
      "writes_training_memory": 0
    },
    {
      "action": "WAIT",
      "best_action_training": "LONG",
      "candidate_conflict_or_new_rate": 0.0,
      "candidate_meaning_preservation_rate": 0.0,
      "candidate_passive_reife_state": "-",
      "candidate_stable_recurrence_rate": 0.0,
      "candidate_temporal_fragility": 0.0,
      "candidate_variant_capacity_rate": 0.0,
      "context_note": "dio_1r1g: keine passive Wiederkehrspur gefunden; nur beobachten.",
      "current_mcm_coherence": 0.299194,
      "current_mcm_tension": 0.325209,
      "current_observation_learning_pressure": 0.333483,
      "current_reflection_alignment": 0.827097,
      "current_trade_readiness": 0.0,
      "influences_action": 0,
      "is_gate": 0,
      "is_motoric": 0,
      "outcome_event": "NO_TRADE",
      "passive_only": 1,
      "read_by_mini_dio": 0,
      "recurrence_context_state": "recurrence_context_unknown",
      "recurrence_maturity_symbol": "-",
      "run": "dio_mini_lauf_1",
      "symbol": "dio_1r1gnnh",
      "symbol_family": "dio_1r1g",
      "tick": "12",
      "timestamp_ms": "1767563600000000",
      "writes_training_memory": 0
    },
    {
      "action": "WAIT",
      "best_action_training": "LONG",
      "candidate_conflict_or_new_rate": 0.0,
      "candidate_meaning_preservation_rate": 0.0,
      "candidate_passive_reife_state": "-",
      "candidate_stable_recurrence_rate": 0.0,
      "candidate_temporal_fragility": 0.0,
      "candidate_variant_capacity_rate": 0.0,
      "context_note": "dio_1ff0: keine passive Wiederkehrspur gefunden; nur beobachten.",
      "current_mcm_coherence": -0.256571,
      "current_mcm_tension": 0.176888,
      "current_observation_learning_pressure": 0.232866,
      "current_reflection_alignment": 0.869214,
      "current_trade_readiness": 0.0,
      "influences_action": 0,
      "is_gate": 0,
      "is_motoric": 0,
      "outcome_event": "NO_TRADE",
      "passive_only": 1,
      "read_by_mini_dio": 0,
      "recurrence_context_state": "recurrence_context_unknown",
      "recurrence_maturity_symbol": "-",
      "run": "dio_mini_lauf_1",
      "symbol": "dio_1ff06cr",
      "symbol_family": "dio_1ff0",
      "tick": "13",
      "timestamp_ms": "1767563900000000",
      "writes_training_memory": 0
    },
    {
      "action": "WAIT",
      "best_action_training": "LONG",
      "candidate_conflict_or_new_rate": 0.0,
      "candidate_meaning_preservation_rate": 1.0,
      "candidate_passive_reife_state": "sinnnah_variantenfaehig",
      "candidate_stable_recurrence_rate": 0.833333,
      "candidate_temporal_fragility": 1.0,
      "candidate_variant_capacity_rate": 0.166667,
      "context_note": "dio_1ekt: sinnnah_variantenfaehig; Sinn-Erhalt=1.000000; stabile Wiederkehr=0.833333; Zeitfragilitaet=1.000000; passive Kontextlesung, keine Handlung.",
      "current_mcm_coherence": 0.371464,
      "current_mcm_tension": 0.272932,
      "current_observation_learning_pressure": 0.430306,
      "current_reflection_alignment": 0.799813,
      "current_trade_readiness": 0.0,
      "influences_action": 0,
      "is_gate": 0,
      "is_motoric": 0,
      "outcome_event": "NO_TRADE",
      "passive_only": 1,
      "read_by_mini_dio": 0,
      "recurrence_context_state": "recurrence_context_meaning_near",
      "recurrence_maturity_symbol": "dio_recur_1i4j2mq",
      "run": "dio_mini_lauf_1",
      "symbol": "dio_1ektc46",
      "symbol_family": "dio_1ekt",
      "tick": "14",
      "timestamp_ms": "1767564200000000",
      "writes_training_memory": 0
    },
    {
      "action": "WAIT",
      "best_action_training": "LONG",
      "candidate_conflict_or_new_rate": 0.0,
      "candidate_meaning_preservation_rate": 0.0,
      "candidate_passive_reife_state": "-",
      "candidate_stable_recurrence_rate": 0.0,
      "candidate_temporal_fragility": 0.0,
      "candidate_variant_capacity_rate": 0.0,
      "context_note": "dio_17ao: keine passive Wiederkehrspur gefunden; nur beobachten.",
      "current_mcm_coherence": 0.925467,
      "current_mcm_tension": 0.532792,
      "current_observation_learning_pressure": 0.63297,
      "current_reflection_alignment": 0.72271,
      "current_trade_readiness": 0.0,
      "influences_action": 0,
      "is_gate": 0,
      "is_motoric": 0,
      "outcome_event": "NO_TRADE",
      "passive_only": 1,
      "read_by_mini_dio": 0,
      "recurrence_context_state": "recurrence_context_unknown",
      "recurrence_maturity_symbol": "-",
      "run": "dio_mini_lauf_1",
      "symbol": "dio_17aodmp",
      "symbol_family": "dio_17ao",
      "tick": "15",
      "timestamp_ms": "1767564500000000",
      "writes_training_memory": 0
    },
    {
      "action": "WAIT",
      "best_action_training": "LONG",
      "candidate_conflict_or_new_rate": 0.0,
      "candidate_meaning_preservation_rate": 0.0,
      "candidate_passive_reife_state": "-",
      "candidate_stable_recurrence_rate": 0.0,
      "candidate_temporal_fragility": 0.0,
      "candidate_variant_capacity_rate": 0.0,
      "context_note": "dio_1t1w: keine passive Wiederkehrspur gefunden; nur beobachten.",
      "current_mcm_coherence": 0.900864,
      "current_mcm_tension": 0.433783,
      "current_observation_learning_pressure": 0.577762,
      "current_reflection_alignment": 0.74327,
      "current_trade_readiness": 0.0,
      "influences_action": 0,
      "is_gate": 0,
      "is_motoric": 0,
      "outcome_event": "NO_TRADE",
      "passive_only": 1,
      "read_by_mini_dio": 0,
      "recurrence_context_state": "recurrence_context_unknown",
      "recurrence_maturity_symbol": "-",
      "run": "dio_mini_lauf_1",
      "symbol": "dio_1t1wbqf",
      "symbol_family": "dio_1t1w",
      "tick": "16",
      "timestamp_ms": "1767564800000000",
      "writes_training_memory": 0
    },
    {
      "action": "WAIT",
      "best_action_training": "LONG",
      "candidate_conflict_or_new_rate": 0.0,
      "candidate_meaning_preservation_rate": 0.0,
      "candidate_passive_reife_state": "-",
      "candidate_stable_recurrence_rate": 0.0,
      "candidate_temporal_fragility": 0.0,
      "candidate_variant_capacity_rate": 0.0,
      "context_note": "dio_1nvu: keine passive Wiederkehrspur gefunden; nur beobachten.",
      "current_mcm_coherence": 0.94429,
      "current_mcm_tension": 0.407508,
      "current_observation_learning_pressure": 0.610033,
      "current_reflection_alignment": 0.734458,
      "current_trade_readiness": 0.0,
      "influences_action": 0,
      "is_gate": 0,
      "is_motoric": 0,
      "outcome_event": "NO_TRADE",
      "passive_only": 1,
      "read_by_mini_dio": 0,
      "recurrence_context_state": "recurrence_context_unknown",
      "recurrence_maturity_symbol": "-",
      "run": "dio_mini_lauf_1",
      "symbol": "dio_1nvu10y",
      "symbol_family": "dio_1nvu",
      "tick": "17",
      "timestamp_ms": "1767565100000000",
      "writes_training_memory": 0
    },
    {
      "action": "WAIT",
      "best_action_training": "SHORT",
      "candidate_conflict_or_new_rate": 0.0,
      "candidate_meaning_preservation_rate": 0.0,
      "candidate_passive_reife_state": "-",
      "candidate_stable_recurrence_rate": 0.0,
      "candidate_temporal_fragility": 0.0,
      "candidate_variant_capacity_rate": 0.0,
      "context_note": "dio_1ldo: keine passive Wiederkehrspur gefunden; nur beobachten.",
      "current_mcm_coherence": 0.977603,
      "current_mcm_tension": 0.413982,
      "current_observation_learning_pressure": 0.634482,
      "current_reflection_alignment": 0.726742,
      "current_trade_readiness": 0.0,
      "influences_action": 0,
      "is_gate": 0,
      "is_motoric": 0,
      "outcome_event": "NO_TRADE",
      "passive_only": 1,
      "read_by_mini_dio": 0,
      "recurrence_context_state": "recurrence_context_unknown",
      "recurrence_maturity_symbol": "-",
      "run": "dio_mini_lauf_1",
      "symbol": "dio_1ldozlb",
      "symbol_family": "dio_1ldo",
      "tick": "18",
      "timestamp_ms": "1767565400000000",
      "writes_training_memory": 0
    },
    {
      "action": "WAIT",
      "best_action_training": "SHORT",
      "candidate_conflict_or_new_rate": 0.0,
      "candidate_meaning_preservation_rate": 0.0,
      "candidate_passive_reife_state": "-",
      "candidate_stable_recurrence_rate": 0.0,
      "candidate_temporal_fragility": 0.0,
      "candidate_variant_capacity_rate": 0.0,
      "context_note": "dio_1rv1: keine passive Wiederkehrspur gefunden; nur beobachten.",
      "current_mcm_coherence": 0.982959,
      "current_mcm_tension": 0.083083,
      "current_observation_learning_pressure": 0.540187,
      "current_reflection_alignment": 0.765123,
      "current_trade_readiness": 0.007428,
      "influences_action": 0,
      "is_gate": 0,
      "is_motoric": 0,
      "outcome_event": "NO_TRADE",
      "passive_only": 1,
      "read_by_mini_dio": 0,
      "recurrence_context_state": "recurrence_context_unknown",
      "recurrence_maturity_symbol": "-",
      "run": "dio_mini_lauf_2",
      "symbol": "dio_1rv13no",
      "symbol_family": "dio_1rv1",
      "tick": "1",
      "timestamp_ms": "1767560300000000",
      "writes_training_memory": 0
    },
    {
      "action": "WAIT",
      "best_action_training": "SHORT",
      "candidate_conflict_or_new_rate": 0.0,
      "candidate_meaning_preservation_rate": 1.0,
      "candidate_passive_reife_state": "sinnnah_variantenfaehig",
      "candidate_stable_recurrence_rate": 0.166667,
      "candidate_temporal_fragility": 1.0,
      "candidate_variant_capacity_rate": 0.833333,
      "context_note": "dio_1ull: sinnnah_variantenfaehig; Sinn-Erhalt=1.000000; stabile Wiederkehr=0.166667; Zeitfragilitaet=1.000000; passive Kontextlesung, keine Handlung.",
      "current_mcm_coherence": -0.233868,
      "current_mcm_tension": 0.104622,
      "current_observation_learning_pressure": 0.212676,
      "current_reflection_alignment": 0.876871,
      "current_trade_readiness": 0.002924,
      "influences_action": 0,
      "is_gate": 0,
      "is_motoric": 0,
      "outcome_event": "NO_TRADE",
      "passive_only": 1,
      "read_by_mini_dio": 0,
      "recurrence_context_state": "recurrence_context_meaning_near",
      "recurrence_maturity_symbol": "dio_recur_18qky6h",
      "run": "dio_mini_lauf_2",
      "symbol": "dio_1ull2yv",
      "symbol_family": "dio_1ull",
      "tick": "2",
      "timestamp_ms": "1767560600000000",
      "writes_training_memory": 0
    },
    {
      "action": "WAIT",
      "best_action_training": "SHORT",
      "candidate_conflict_or_new_rate": 0.0,
      "candidate_meaning_preservation_rate": 0.0,
      "candidate_passive_reife_state": "-",
      "candidate_stable_recurrence_rate": 0.0,
      "candidate_temporal_fragility": 0.0,
      "candidate_variant_capacity_rate": 0.0,
      "context_note": "dio_14c1: keine passive Wiederkehrspur gefunden; nur beobachten.",
      "current_mcm_coherence": 0.097707,
      "current_mcm_tension": 0.356234,
      "current_observation_learning_pressure": 0.321225,
      "current_reflection_alignment": 0.829917,
      "current_trade_readiness": 0.004417,
      "influences_action": 0,
      "is_gate": 0,
      "is_motoric": 0,
      "outcome_event": "NO_TRADE",
      "passive_only": 1,
      "read_by_mini_dio": 0,
      "recurrence_context_state": "recurrence_context_unknown",
      "recurrence_maturity_symbol": "-",
      "run": "dio_mini_lauf_2",
      "symbol": "dio_14c1zmg",
      "symbol_family": "dio_14c1",
      "tick": "3",
      "timestamp_ms": "1767560900000000",
      "writes_training_memory": 0
    },
    {
      "action": "WAIT",
      "best_action_training": "LONG",
      "candidate_conflict_or_new_rate": 0.166667,
      "candidate_meaning_preservation_rate": 0.833333,
      "candidate_passive_reife_state": "sinnnah_variantenfaehig",
      "candidate_stable_recurrence_rate": 0.666667,
      "candidate_temporal_fragility": 1.0,
      "candidate_variant_capacity_rate": 0.166667,
      "context_note": "dio_05k3: sinnnah_variantenfaehig; Sinn-Erhalt=0.833333; stabile Wiederkehr=0.666667; Zeitfragilitaet=1.000000; passive Kontextlesung, keine Handlung.",
      "current_mcm_coherence": 0.289756,
      "current_mcm_tension": 0.470591,
      "current_observation_learning_pressure": 0.408467,
      "current_reflection_alignment": 0.798975,
      "current_trade_readiness": 0.005616,
      "influences_action": 0,
      "is_gate": 0,
      "is_motoric": 0,
      "outcome_event": "NO_TRADE",
      "passive_only": 1,
      "read_by_mini_dio": 0,
      "recurrence_context_state": "recurrence_context_meaning_near",
      "recurrence_maturity_symbol": "dio_recur_x7exs",
      "run": "dio_mini_lauf_2",
      "symbol": "dio_05k373k",
      "symbol_family": "dio_05k3",
      "tick": "4",
      "timestamp_ms": "1767561200000000",
      "writes_training_memory": 0
    },
    {
      "action": "WAIT",
      "best_action_training": "LONG",
      "candidate_conflict_or_new_rate": 0.0,
      "candidate_meaning_preservation_rate": 0.0,
      "candidate_passive_reife_state": "-",
      "candidate_stable_recurrence_rate": 0.0,
      "candidate_temporal_fragility": 0.0,
      "candidate_variant_capacity_rate": 0.0,
      "context_note": "dio_1tsz: keine passive Wiederkehrspur gefunden; nur beobachten.",
      "current_mcm_coherence": 0.992977,
      "current_mcm_tension": 0.362566,
      "current_observation_learning_pressure": 0.62276,
      "current_reflection_alignment": 0.728861,
      "current_trade_readiness": 0.008563,
      "influences_action": 0,
      "is_gate": 0,
      "is_motoric": 0,
      "outcome_event": "NO_TRADE",
      "passive_only": 1,
      "read_by_mini_dio": 0,
      "recurrence_context_state": "recurrence_context_unknown",
      "recurrence_maturity_symbol": "-",
      "run": "dio_mini_lauf_2",
      "symbol": "dio_1tszbgb",
      "symbol_family": "dio_1tsz",
      "tick": "5",
      "timestamp_ms": "1767561500000000",
      "writes_training_memory": 0
    },
    {
      "action": "WAIT",
      "best_action_training": "LONG",
      "candidate_conflict_or_new_rate": 0.0,
      "candidate_meaning_preservation_rate": 0.0,
      "candidate_passive_reife_state": "-",
      "candidate_stable_recurrence_rate": 0.0,
      "candidate_temporal_fragility": 0.0,
      "candidate_variant_capacity_rate": 0.0,
      "context_note": "dio_1jba: keine passive Wiederkehrspur gefunden; nur beobachten.",
      "current_mcm_coherence": 0.392717,
      "current_mcm_tension": 0.344782,
      "current_observation_learning_pressure": 0.417723,
      "current_reflection_alignment": 0.798441,
      "current_trade_readiness": 0.005744,
      "influences_action": 0,
      "is_gate": 0,
      "is_motoric": 0,
      "outcome_event": "NO_TRADE",
      "passive_only": 1,
      "read_by_mini_dio": 0,
      "recurrence_context_state": "recurrence_context_unknown",
      "recurrence_maturity_symbol": "-",
      "run": "dio_mini_lauf_2",
      "symbol": "dio_1jbaunv",
      "symbol_family": "dio_1jba",
      "tick": "6",
      "timestamp_ms": "1767561800000000",
      "writes_training_memory": 0
    },
    {
      "action": "WAIT",
      "best_action_training": "SHORT",
      "candidate_conflict_or_new_rate": 0.0,
      "candidate_meaning_preservation_rate": 0.0,
      "candidate_passive_reife_state": "-",
      "candidate_stable_recurrence_rate": 0.0,
      "candidate_temporal_fragility": 0.0,
      "candidate_variant_capacity_rate": 0.0,
      "context_note": "dio_0ic5: keine passive Wiederkehrspur gefunden; nur beobachten.",
      "current_mcm_coherence": -0.209546,
      "current_mcm_tension": 0.128454,
      "current_observation_learning_pressure": 0.218907,
      "current_reflection_alignment": 0.873938,
      "current_trade_readiness": 0.00301,
      "influences_action": 0,
      "is_gate": 0,
      "is_motoric": 0,
      "outcome_event": "NO_TRADE",
      "passive_only": 1,
      "read_by_mini_dio": 0,
      "recurrence_context_state": "recurrence_context_unknown",
      "recurrence_maturity_symbol": "-",
      "run": "dio_mini_lauf_2",
      "symbol": "dio_0ic5er6",
      "symbol_family": "dio_0ic5",
      "tick": "7",
      "timestamp_ms": "1767562100000000",
      "writes_training_memory": 0
    },
    {
      "action": "WAIT",
      "best_action_training": "SHORT",
      "candidate_conflict_or_new_rate": 0.0,
      "candidate_meaning_preservation_rate": 0.0,
      "candidate_passive_reife_state": "-",
      "candidate_stable_recurrence_rate": 0.0,
      "candidate_temporal_fragility": 0.0,
      "candidate_variant_capacity_rate": 0.0,
      "context_note": "dio_0s84: keine passive Wiederkehrspur gefunden; nur beobachten.",
      "current_mcm_coherence": 0.395847,
      "current_mcm_tension": 0.262513,
      "current_observation_learning_pressure": 0.4449,
      "current_reflection_alignment": 0.79337,
      "current_trade_readiness": 0.006117,
      "influences_action": 0,
      "is_gate": 0,
      "is_motoric": 0,
      "outcome_event": "NO_TRADE",
      "passive_only": 1,
      "read_by_mini_dio": 0,
      "recurrence_context_state": "recurrence_context_unknown",
      "recurrence_maturity_symbol": "-",
      "run": "dio_mini_lauf_2",
      "symbol": "dio_0s84lnj",
      "symbol_family": "dio_0s84",
      "tick": "8",
      "timestamp_ms": "1767562400000000",
      "writes_training_memory": 0
    },
    {
      "action": "WAIT",
      "best_action_training": "SHORT",
      "candidate_conflict_or_new_rate": 0.0,
      "candidate_meaning_preservation_rate": 1.0,
      "candidate_passive_reife_state": "sinnnah_variantenfaehig",
      "candidate_stable_recurrence_rate": 0.166667,
      "candidate_temporal_fragility": 1.0,
      "candidate_variant_capacity_rate": 0.833333,
      "context_note": "dio_19mp: sinnnah_variantenfaehig; Sinn-Erhalt=1.000000; stabile Wiederkehr=0.166667; Zeitfragilitaet=1.000000; passive Kontextlesung, keine Handlung.",
      "current_mcm_coherence": 0.372062,
      "current_mcm_tension": 0.376867,
      "current_observation_learning_pressure": 0.431111,
      "current_reflection_alignment": 0.793177,
      "current_trade_readiness": 0.005928,
      "influences_action": 0,
      "is_gate": 0,
      "is_motoric": 0,
      "outcome_event": "NO_TRADE",
      "passive_only": 1,
      "read_by_mini_dio": 0,
      "recurrence_context_state": "recurrence_context_meaning_near",
      "recurrence_maturity_symbol": "dio_recur_cslksc",
      "run": "dio_mini_lauf_2",
      "symbol": "dio_19mpp0p",
      "symbol_family": "dio_19mp",
      "tick": "9",
      "timestamp_ms": "1767562700000000",
      "writes_training_memory": 0
    },
    {
      "action": "WAIT",
      "best_action_training": "LONG",
      "candidate_conflict_or_new_rate": 0.166667,
      "candidate_meaning_preservation_rate": 0.833333,
      "candidate_passive_reife_state": "sinnnah_variantenfaehig",
      "candidate_stable_recurrence_rate": 0.166667,
      "candidate_temporal_fragility": 1.0,
      "candidate_variant_capacity_rate": 0.666667,
      "context_note": "dio_1hs5: sinnnah_variantenfaehig; Sinn-Erhalt=0.833333; stabile Wiederkehr=0.166667; Zeitfragilitaet=1.000000; passive Kontextlesung, keine Handlung.",
      "current_mcm_coherence": -0.220085,
      "current_mcm_tension": 0.194834,
      "current_observation_learning_pressure": 0.222348,
      "current_reflection_alignment": 0.870317,
      "current_trade_readiness": 0.003057,
      "influences_action": 0,
      "is_gate": 0,
      "is_motoric": 0,
      "outcome_event": "NO_TRADE",
      "passive_only": 1,
      "read_by_mini_dio": 0,
      "recurrence_context_state": "recurrence_context_meaning_near",
      "recurrence_maturity_symbol": "dio_recur_2rlxa4",
      "run": "dio_mini_lauf_2",
      "symbol": "dio_1hs5sz6",
      "symbol_family": "dio_1hs5",
      "tick": "10",
      "timestamp_ms": "1767563000000000",
      "writes_training_memory": 0
    },
    {
      "action": "WAIT",
      "best_action_training": "LONG",
      "candidate_conflict_or_new_rate": 0.0,
      "candidate_meaning_preservation_rate": 0.0,
      "candidate_passive_reife_state": "-",
      "candidate_stable_recurrence_rate": 0.0,
      "candidate_temporal_fragility": 0.0,
      "candidate_variant_capacity_rate": 0.0,
      "context_note": "dio_12dn: keine passive Wiederkehrspur gefunden; nur beobachten.",
      "current_mcm_coherence": 0.369061,
      "current_mcm_tension": 0.254875,
      "current_observation_learning_pressure": 0.407381,
      "current_reflection_alignment": 0.80522,
      "current_trade_readiness": 0.005601,
      "influences_action": 0,
      "is_gate": 0,
      "is_motoric": 0,
      "outcome_event": "NO_TRADE",
      "passive_only": 1,
      "read_by_mini_dio": 0,
      "recurrence_context_state": "recurrence_context_unknown",
      "recurrence_maturity_symbol": "-",
      "run": "dio_mini_lauf_2",
      "symbol": "dio_12dnns3",
      "symbol_family": "dio_12dn",
      "tick": "11",
      "timestamp_ms": "1767563300000000",
      "writes_training_memory": 0
    },
    {
      "action": "WAIT",
      "best_action_training": "LONG",
      "candidate_conflict_or_new_rate": 0.0,
      "candidate_meaning_preservation_rate": 0.0,
      "candidate_passive_reife_state": "-",
      "candidate_stable_recurrence_rate": 0.0,
      "candidate_temporal_fragility": 0.0,
      "candidate_variant_capacity_rate": 0.0,
      "context_note": "dio_1r1g: keine passive Wiederkehrspur gefunden; nur beobachten.",
      "current_mcm_coherence": 0.299194,
      "current_mcm_tension": 0.325209,
      "current_observation_learning_pressure": 0.333483,
      "current_reflection_alignment": 0.825303,
      "current_trade_readiness": 0.004585,
      "influences_action": 0,
      "is_gate": 0,
      "is_motoric": 0,
      "outcome_event": "NO_TRADE",
      "passive_only": 1,
      "read_by_mini_dio": 0,
      "recurrence_context_state": "recurrence_context_unknown",
      "recurrence_maturity_symbol": "-",
      "run": "dio_mini_lauf_2",
      "symbol": "dio_1r1gnnh",
      "symbol_family": "dio_1r1g",
      "tick": "12",
      "timestamp_ms": "1767563600000000",
      "writes_training_memory": 0
    },
    {
      "action": "WAIT",
      "best_action_training": "LONG",
      "candidate_conflict_or_new_rate": 0.0,
      "candidate_meaning_preservation_rate": 0.0,
      "candidate_passive_reife_state": "-",
      "candidate_stable_recurrence_rate": 0.0,
      "candidate_temporal_fragility": 0.0,
      "candidate_variant_capacity_rate": 0.0,
      "context_note": "dio_1ff0: keine passive Wiederkehrspur gefunden; nur beobachten.",
      "current_mcm_coherence": -0.256571,
      "current_mcm_tension": 0.176888,
      "current_observation_learning_pressure": 0.232866,
      "current_reflection_alignment": 0.867956,
      "current_trade_readiness": 0.003202,
      "influences_action": 0,
      "is_gate": 0,
      "is_motoric": 0,
      "outcome_event": "NO_TRADE",
      "passive_only": 1,
      "read_by_mini_dio": 0,
      "recurrence_context_state": "recurrence_context_unknown",
      "recurrence_maturity_symbol": "-",
      "run": "dio_mini_lauf_2",
      "symbol": "dio_1ff06cr",
      "symbol_family": "dio_1ff0",
      "tick": "13",
      "timestamp_ms": "1767563900000000",
      "writes_training_memory": 0
    },
    {
      "action": "WAIT",
      "best_action_training": "LONG",
      "candidate_conflict_or_new_rate": 0.0,
      "candidate_meaning_preservation_rate": 1.0,
      "candidate_passive_reife_state": "sinnnah_variantenfaehig",
      "candidate_stable_recurrence_rate": 0.833333,
      "candidate_temporal_fragility": 1.0,
      "candidate_variant_capacity_rate": 0.166667,
      "context_note": "dio_1ekt: sinnnah_variantenfaehig; Sinn-Erhalt=1.000000; stabile Wiederkehr=0.833333; Zeitfragilitaet=1.000000; passive Kontextlesung, keine Handlung.",
      "current_mcm_coherence": 0.371464,
      "current_mcm_tension": 0.272932,
      "current_observation_learning_pressure": 0.430306,
      "current_reflection_alignment": 0.797498,
      "current_trade_readiness": 0.005917,
      "influences_action": 0,
      "is_gate": 0,
      "is_motoric": 0,
      "outcome_event": "NO_TRADE",
      "passive_only": 1,
      "read_by_mini_dio": 0,
      "recurrence_context_state": "recurrence_context_meaning_near",
      "recurrence_maturity_symbol": "dio_recur_1i4j2mq",
      "run": "dio_mini_lauf_2",
      "symbol": "dio_1ektc46",
      "symbol_family": "dio_1ekt",
      "tick": "14",
      "timestamp_ms": "1767564200000000",
      "writes_training_memory": 0
    },
    {
      "action": "WAIT",
      "best_action_training": "LONG",
      "candidate_conflict_or_new_rate": 0.0,
      "candidate_meaning_preservation_rate": 0.0,
      "candidate_passive_reife_state": "-",
      "candidate_stable_recurrence_rate": 0.0,
      "candidate_temporal_fragility": 0.0,
      "candidate_variant_capacity_rate": 0.0,
      "context_note": "dio_17ao: keine passive Wiederkehrspur gefunden; nur beobachten.",
      "current_mcm_coherence": 0.925467,
      "current_mcm_tension": 0.532792,
      "current_observation_learning_pressure": 0.63297,
      "current_reflection_alignment": 0.719305,
      "current_trade_readiness": 0.008703,
      "influences_action": 0,
      "is_gate": 0,
      "is_motoric": 0,
      "outcome_event": "NO_TRADE",
      "passive_only": 1,
      "read_by_mini_dio": 0,
      "recurrence_context_state": "recurrence_context_unknown",
      "recurrence_maturity_symbol": "-",
      "run": "dio_mini_lauf_2",
      "symbol": "dio_17aodmp",
      "symbol_family": "dio_17ao",
      "tick": "15",
      "timestamp_ms": "1767564500000000",
      "writes_training_memory": 0
    },
    {
      "action": "WAIT",
      "best_action_training": "LONG",
      "candidate_conflict_or_new_rate": 0.0,
      "candidate_meaning_preservation_rate": 0.0,
      "candidate_passive_reife_state": "-",
      "candidate_stable_recurrence_rate": 0.0,
      "candidate_temporal_fragility": 0.0,
      "candidate_variant_capacity_rate": 0.0,
      "context_note": "dio_1t1w: keine passive Wiederkehrspur gefunden; nur beobachten.",
      "current_mcm_coherence": 0.900864,
      "current_mcm_tension": 0.433783,
      "current_observation_learning_pressure": 0.577762,
      "current_reflection_alignment": 0.740161,
      "current_trade_readiness": 0.007944,
      "influences_action": 0,
      "is_gate": 0,
      "is_motoric": 0,
      "outcome_event": "NO_TRADE",
      "passive_only": 1,
      "read_by_mini_dio": 0,
      "recurrence_context_state": "recurrence_context_unknown",
      "recurrence_maturity_symbol": "-",
      "run": "dio_mini_lauf_2",
      "symbol": "dio_1t1wbqf",
      "symbol_family": "dio_1t1w",
      "tick": "16",
      "timestamp_ms": "1767564800000000",
      "writes_training_memory": 0
    },
    {
      "action": "WAIT",
      "best_action_training": "LONG",
      "candidate_conflict_or_new_rate": 0.0,
      "candidate_meaning_preservation_rate": 0.0,
      "candidate_passive_reife_state": "-",
      "candidate_stable_recurrence_rate": 0.0,
      "candidate_temporal_fragility": 0.0,
      "candidate_variant_capacity_rate": 0.0,
      "context_note": "dio_1nvu: keine passive Wiederkehrspur gefunden; nur beobachten.",
      "current_mcm_coherence": 0.94429,
      "current_mcm_tension": 0.407508,
      "current_observation_learning_pressure": 0.610033,
      "current_reflection_alignment": 0.731176,
      "current_trade_readiness": 0.008388,
      "influences_action": 0,
      "is_gate": 0,
      "is_motoric": 0,
      "outcome_event": "NO_TRADE",
      "passive_only": 1,
      "read_by_mini_dio": 0,
      "recurrence_context_state": "recurrence_context_unknown",
      "recurrence_maturity_symbol": "-",
      "run": "dio_mini_lauf_2",
      "symbol": "dio_1nvu10y",
      "symbol_family": "dio_1nvu",
      "tick": "17",
      "timestamp_ms": "1767565100000000",
      "writes_training_memory": 0
    },
    {
      "action": "WAIT",
      "best_action_training": "SHORT",
      "candidate_conflict_or_new_rate": 0.0,
      "candidate_meaning_preservation_rate": 0.0,
      "candidate_passive_reife_state": "-",
      "candidate_stable_recurrence_rate": 0.0,
      "candidate_temporal_fragility": 0.0,
      "candidate_variant_capacity_rate": 0.0,
      "context_note": "dio_1ldo: keine passive Wiederkehrspur gefunden; nur beobachten.",
      "current_mcm_coherence": 0.977603,
      "current_mcm_tension": 0.413982,
      "current_observation_learning_pressure": 0.634482,
      "current_reflection_alignment": 0.723346,
      "current_trade_readiness": 0.008724,
      "influences_action": 0,
      "is_gate": 0,
      "is_motoric": 0,
      "outcome_event": "NO_TRADE",
      "passive_only": 1,
      "read_by_mini_dio": 0,
      "recurrence_context_state": "recurrence_context_unknown",
      "recurrence_maturity_symbol": "-",
      "run": "dio_mini_lauf_2",
      "symbol": "dio_1ldozlb",
      "symbol_family": "dio_1ldo",
      "tick": "18",
      "timestamp_ms": "1767565400000000",
      "writes_training_memory": 0
    }
  ],
  "schema": "dio_mini_passive_recurrence_maturity_context.v1",
  "summary": [
    {
      "avg_observation_learning_pressure": 0.430306,
      "avg_reflection_alignment": 0.7986555,
      "avg_trade_readiness": 0.0029585,
      "candidate_meaning_preservation_rate": 1.0,
      "candidate_passive_reife_state": "sinnnah_variantenfaehig",
      "candidate_stable_recurrence_rate": 0.833333,
      "candidate_temporal_fragility": 1.0,
      "context_state_counts": "recurrence_context_meaning_near:2",
      "dominant_recurrence_context_state": "recurrence_context_meaning_near",
      "episodes": 2,
      "influences_action": 0,
      "is_gate": 0,
      "is_motoric": 0,
      "passive_only": 1,
      "read_by_mini_dio": 0,
      "run_count": 2,
      "symbol_family": "dio_1ekt",
      "writes_training_memory": 0
    },
    {
      "avg_observation_learning_pressure": 0.431111,
      "avg_reflection_alignment": 0.7943315,
      "avg_trade_readiness": 0.002964,
      "candidate_meaning_preservation_rate": 1.0,
      "candidate_passive_reife_state": "sinnnah_variantenfaehig",
      "candidate_stable_recurrence_rate": 0.166667,
      "candidate_temporal_fragility": 1.0,
      "context_state_counts": "recurrence_context_meaning_near:2",
      "dominant_recurrence_context_state": "recurrence_context_meaning_near",
      "episodes": 2,
      "influences_action": 0,
      "is_gate": 0,
      "is_motoric": 0,
      "passive_only": 1,
      "read_by_mini_dio": 0,
      "run_count": 2,
      "symbol_family": "dio_19mp",
      "writes_training_memory": 0
    },
    {
      "avg_observation_learning_pressure": 0.212676,
      "avg_reflection_alignment": 0.8774475,
      "avg_trade_readiness": 0.001462,
      "candidate_meaning_preservation_rate": 1.0,
      "candidate_passive_reife_state": "sinnnah_variantenfaehig",
      "candidate_stable_recurrence_rate": 0.166667,
      "candidate_temporal_fragility": 1.0,
      "context_state_counts": "recurrence_context_meaning_near:2",
      "dominant_recurrence_context_state": "recurrence_context_meaning_near",
      "episodes": 2,
      "influences_action": 0,
      "is_gate": 0,
      "is_motoric": 0,
      "passive_only": 1,
      "read_by_mini_dio": 0,
      "run_count": 2,
      "symbol_family": "dio_1ull",
      "writes_training_memory": 0
    },
    {
      "avg_observation_learning_pressure": 0.408467,
      "avg_reflection_alignment": 0.8001535,
      "avg_trade_readiness": 0.002808,
      "candidate_meaning_preservation_rate": 0.833333,
      "candidate_passive_reife_state": "sinnnah_variantenfaehig",
      "candidate_stable_recurrence_rate": 0.666667,
      "candidate_temporal_fragility": 1.0,
      "context_state_counts": "recurrence_context_meaning_near:2",
      "dominant_recurrence_context_state": "recurrence_context_meaning_near",
      "episodes": 2,
      "influences_action": 0,
      "is_gate": 0,
      "is_motoric": 0,
      "passive_only": 1,
      "read_by_mini_dio": 0,
      "run_count": 2,
      "symbol_family": "dio_05k3",
      "writes_training_memory": 0
    },
    {
      "avg_observation_learning_pressure": 0.222348,
      "avg_reflection_alignment": 0.8709205,
      "avg_trade_readiness": 0.0015285,
      "candidate_meaning_preservation_rate": 0.833333,
      "candidate_passive_reife_state": "sinnnah_variantenfaehig",
      "candidate_stable_recurrence_rate": 0.166667,
      "candidate_temporal_fragility": 1.0,
      "context_state_counts": "recurrence_context_meaning_near:2",
      "dominant_recurrence_context_state": "recurrence_context_meaning_near",
      "episodes": 2,
      "influences_action": 0,
      "is_gate": 0,
      "is_motoric": 0,
      "passive_only": 1,
      "read_by_mini_dio": 0,
      "run_count": 2,
      "symbol_family": "dio_1hs5",
      "writes_training_memory": 0
    },
    {
      "avg_observation_learning_pressure": 0.218907,
      "avg_reflection_alignment": 0.8745285,
      "avg_trade_readiness": 0.001505,
      "candidate_meaning_preservation_rate": 0.0,
      "candidate_passive_reife_state": "-",
      "candidate_stable_recurrence_rate": 0.0,
      "candidate_temporal_fragility": 0.0,
      "context_state_counts": "recurrence_context_unknown:2",
      "dominant_recurrence_context_state": "recurrence_context_unknown",
      "episodes": 2,
      "influences_action": 0,
      "is_gate": 0,
      "is_motoric": 0,
      "passive_only": 1,
      "read_by_mini_dio": 0,
      "run_count": 2,
      "symbol_family": "dio_0ic5",
      "writes_training_memory": 0
    },
    {
      "avg_observation_learning_pressure": 0.4449,
      "avg_reflection_alignment": 0.7945615,
      "avg_trade_readiness": 0.0030585,
      "candidate_meaning_preservation_rate": 0.0,
      "candidate_passive_reife_state": "-",
      "candidate_stable_recurrence_rate": 0.0,
      "candidate_temporal_fragility": 0.0,
      "context_state_counts": "recurrence_context_unknown:2",
      "dominant_recurrence_context_state": "recurrence_context_unknown",
      "episodes": 2,
      "influences_action": 0,
      "is_gate": 0,
      "is_motoric": 0,
      "passive_only": 1,
      "read_by_mini_dio": 0,
      "run_count": 2,
      "symbol_family": "dio_0s84",
      "writes_training_memory": 0
    },
    {
      "avg_observation_learning_pressure": 0.407381,
      "avg_reflection_alignment": 0.806316,
      "avg_trade_readiness": 0.0028005,
      "candidate_meaning_preservation_rate": 0.0,
      "candidate_passive_reife_state": "-",
      "candidate_stable_recurrence_rate": 0.0,
      "candidate_temporal_fragility": 0.0,
      "context_state_counts": "recurrence_context_unknown:2",
      "dominant_recurrence_context_state": "recurrence_context_unknown",
      "episodes": 2,
      "influences_action": 0,
      "is_gate": 0,
      "is_motoric": 0,
      "passive_only": 1,
      "read_by_mini_dio": 0,
      "run_count": 2,
      "symbol_family": "dio_12dn",
      "writes_training_memory": 0
    },
    {
      "avg_observation_learning_pressure": 0.321225,
      "avg_reflection_alignment": 0.8307865,
      "avg_trade_readiness": 0.0022085,
      "candidate_meaning_preservation_rate": 0.0,
      "candidate_passive_reife_state": "-",
      "candidate_stable_recurrence_rate": 0.0,
      "candidate_temporal_fragility": 0.0,
      "context_state_counts": "recurrence_context_unknown:2",
      "dominant_recurrence_context_state": "recurrence_context_unknown",
      "episodes": 2,
      "influences_action": 0,
      "is_gate": 0,
      "is_motoric": 0,
      "passive_only": 1,
      "read_by_mini_dio": 0,
      "run_count": 2,
      "symbol_family": "dio_14c1",
      "writes_training_memory": 0
    },
    {
      "avg_observation_learning_pressure": 0.63297,
      "avg_reflection_alignment": 0.7210075,
      "avg_trade_readiness": 0.0043515,
      "candidate_meaning_preservation_rate": 0.0,
      "candidate_passive_reife_state": "-",
      "candidate_stable_recurrence_rate": 0.0,
      "candidate_temporal_fragility": 0.0,
      "context_state_counts": "recurrence_context_unknown:2",
      "dominant_recurrence_context_state": "recurrence_context_unknown",
      "episodes": 2,
      "influences_action": 0,
      "is_gate": 0,
      "is_motoric": 0,
      "passive_only": 1,
      "read_by_mini_dio": 0,
      "run_count": 2,
      "symbol_family": "dio_17ao",
      "writes_training_memory": 0
    },
    {
      "avg_observation_learning_pressure": 0.232866,
      "avg_reflection_alignment": 0.868585,
      "avg_trade_readiness": 0.001601,
      "candidate_meaning_preservation_rate": 0.0,
      "candidate_passive_reife_state": "-",
      "candidate_stable_recurrence_rate": 0.0,
      "candidate_temporal_fragility": 0.0,
      "context_state_counts": "recurrence_context_unknown:2",
      "dominant_recurrence_context_state": "recurrence_context_unknown",
      "episodes": 2,
      "influences_action": 0,
      "is_gate": 0,
      "is_motoric": 0,
      "passive_only": 1,
      "read_by_mini_dio": 0,
      "run_count": 2,
      "symbol_family": "dio_1ff0",
      "writes_training_memory": 0
    },
    {
      "avg_observation_learning_pressure": 0.417723,
      "avg_reflection_alignment": 0.7995625,
      "avg_trade_readiness": 0.002872,
      "candidate_meaning_preservation_rate": 0.0,
      "candidate_passive_reife_state": "-",
      "candidate_stable_recurrence_rate": 0.0,
      "candidate_temporal_fragility": 0.0,
      "context_state_counts": "recurrence_context_unknown:2",
      "dominant_recurrence_context_state": "recurrence_context_unknown",
      "episodes": 2,
      "influences_action": 0,
      "is_gate": 0,
      "is_motoric": 0,
      "passive_only": 1,
      "read_by_mini_dio": 0,
      "run_count": 2,
      "symbol_family": "dio_1jba",
      "writes_training_memory": 0
    },
    {
      "avg_observation_learning_pressure": 0.634482,
      "avg_reflection_alignment": 0.725044,
      "avg_trade_readiness": 0.004362,
      "candidate_meaning_preservation_rate": 0.0,
      "candidate_passive_reife_state": "-",
      "candidate_stable_recurrence_rate": 0.0,
      "candidate_temporal_fragility": 0.0,
      "context_state_counts": "recurrence_context_unknown:2",
      "dominant_recurrence_context_state": "recurrence_context_unknown",
      "episodes": 2,
      "influences_action": 0,
      "is_gate": 0,
      "is_motoric": 0,
      "passive_only": 1,
      "read_by_mini_dio": 0,
      "run_count": 2,
      "symbol_family": "dio_1ldo",
      "writes_training_memory": 0
    },
    {
      "avg_observation_learning_pressure": 0.610033,
      "avg_reflection_alignment": 0.732817,
      "avg_trade_readiness": 0.004194,
      "candidate_meaning_preservation_rate": 0.0,
      "candidate_passive_reife_state": "-",
      "candidate_stable_recurrence_rate": 0.0,
      "candidate_temporal_fragility": 0.0,
      "context_state_counts": "recurrence_context_unknown:2",
      "dominant_recurrence_context_state": "recurrence_context_unknown",
      "episodes": 2,
      "influences_action": 0,
      "is_gate": 0,
      "is_motoric": 0,
      "passive_only": 1,
      "read_by_mini_dio": 0,
      "run_count": 2,
      "symbol_family": "dio_1nvu",
      "writes_training_memory": 0
    },
    {
      "avg_observation_learning_pressure": 0.333483,
      "avg_reflection_alignment": 0.8262,
      "avg_trade_readiness": 0.0022925,
      "candidate_meaning_preservation_rate": 0.0,
      "candidate_passive_reife_state": "-",
      "candidate_stable_recurrence_rate": 0.0,
      "candidate_temporal_fragility": 0.0,
      "context_state_counts": "recurrence_context_unknown:2",
      "dominant_recurrence_context_state": "recurrence_context_unknown",
      "episodes": 2,
      "influences_action": 0,
      "is_gate": 0,
      "is_motoric": 0,
      "passive_only": 1,
      "read_by_mini_dio": 0,
      "run_count": 2,
      "symbol_family": "dio_1r1g",
      "writes_training_memory": 0
    },
    {
      "avg_observation_learning_pressure": 0.540187,
      "avg_reflection_alignment": 0.7665715,
      "avg_trade_readiness": 0.003714,
      "candidate_meaning_preservation_rate": 0.0,
      "candidate_passive_reife_state": "-",
      "candidate_stable_recurrence_rate": 0.0,
      "candidate_temporal_fragility": 0.0,
      "context_state_counts": "recurrence_context_unknown:2",
      "dominant_recurrence_context_state": "recurrence_context_unknown",
      "episodes": 2,
      "influences_action": 0,
      "is_gate": 0,
      "is_motoric": 0,
      "passive_only": 1,
      "read_by_mini_dio": 0,
      "run_count": 2,
      "symbol_family": "dio_1rv1",
      "writes_training_memory": 0
    },
    {
      "avg_observation_learning_pressure": 0.577762,
      "avg_reflection_alignment": 0.7417155,
      "avg_trade_readiness": 0.003972,
      "candidate_meaning_preservation_rate": 0.0,
      "candidate_passive_reife_state": "-",
      "candidate_stable_recurrence_rate": 0.0,
      "candidate_temporal_fragility": 0.0,
      "context_state_counts": "recurrence_context_unknown:2",
      "dominant_recurrence_context_state": "recurrence_context_unknown",
      "episodes": 2,
      "influences_action": 0,
      "is_gate": 0,
      "is_motoric": 0,
      "passive_only": 1,
      "read_by_mini_dio": 0,
      "run_count": 2,
      "symbol_family": "dio_1t1w",
      "writes_training_memory": 0
    },
    {
      "avg_observation_learning_pressure": 0.62276,
      "avg_reflection_alignment": 0.7305365,
      "avg_trade_readiness": 0.0042815,
      "candidate_meaning_preservation_rate": 0.0,
      "candidate_passive_reife_state": "-",
      "candidate_stable_recurrence_rate": 0.0,
      "candidate_temporal_fragility": 0.0,
      "context_state_counts": "recurrence_context_unknown:2",
      "dominant_recurrence_context_state": "recurrence_context_unknown",
      "episodes": 2,
      "influences_action": 0,
      "is_gate": 0,
      "is_motoric": 0,
      "passive_only": 1,
      "read_by_mini_dio": 0,
      "run_count": 2,
      "symbol_family": "dio_1tsz",
      "writes_training_memory": 0
    }
  ]
}